universal/conf.py
universal/version.py
universal/grains/universal/init.py
universal/grains/universal/path.py
universal/grains/universal/requirement_versions.py
grains_universal-3.dist-info/METADATA
grains_universal-3.dist-info/WHEEL
grains_universal-3.dist-info/top_level.txt
grains_universal-3.dist-info/RECORD
