Metadata-Version: 2.1
Name: grains-universal
Version: 3
Summary: Vertical app merge components for grains on all systems
Home-page: UNKNOWN
Author: Tyler Johnson
Author-email: tjohnson@saltstack.com
License: UNKNOWN
Platform: UNKNOWN
Classifier: Operating System :: OS Independent
Classifier: Programming Language :: Python
Classifier: Programming Language :: Python :: 3.6
Classifier: Programming Language :: Python :: 3.7
Classifier: Programming Language :: Python :: 3.8
Classifier: Development Status :: 5 - Production/Stable
Requires-Python: >=3.6
Requires-Dist: aiofiles (>=0.3.0)
Requires-Dist: dict-toolbox (>=1.8)
Requires-Dist: grainsv2 (>=10.1)
Requires-Dist: python-dateutil (>=1.4)
